tw2/__init__.py
tw2/recaptcha2/__init__.py
tw2/recaptcha2/resources.py
tw2/recaptcha2/validator.py
tw2/recaptcha2/widgets.py
tw2/recaptcha2/templates/__init__.py
tw2/recaptcha2/templates/recaptcha2.html
tw2/recaptcha2/templates/recaptcha2.jinja
tw2/recaptcha2/templates/recaptcha2.kajiki
tw2/recaptcha2/templates/recaptcha2.mak
tw2.recaptcha2-0.1.dist-info/COPYING
tw2.recaptcha2-0.1.dist-info/METADATA
tw2.recaptcha2-0.1.dist-info/WHEEL
tw2.recaptcha2-0.1.dist-info/entry_points.txt
tw2.recaptcha2-0.1.dist-info/top_level.txt
tw2.recaptcha2-0.1.dist-info/RECORD
